tool_usage_evals/__init__.py
tool_usage_evals/mcp_handling.py
tool_usage_evals/multi_step.py
tool_usage_evals/single_step.py
tool_usage_evals/utils.py
tool_usage_evals-0.1.4.dist-info/METADATA
tool_usage_evals-0.1.4.dist-info/WHEEL
tool_usage_evals-0.1.4.dist-info/licenses/LICENSE
tool_usage_evals-0.1.4.dist-info/RECORD
