Metadata-Version: 2.4
Name: tool-usage-evals
Version: 0.1.4
Summary: Add your description here
License-File: LICENSE
Requires-Python: >=3.10
Requires-Dist: azure-identity>=1.23.0
Requires-Dist: mcp>=1.9.1
Requires-Dist: openai>=1.82.0
Requires-Dist: pydantic>=2.11.5
Requires-Dist: python-dotenv>=1.1.0
Requires-Dist: tenacity>=9.1.2
